strukt/__init__.py
strukt/ai.py
strukt/cli.py
strukt/config.py
strukt/defaults.py
strukt/engine.py
strukt/evaluation.py
strukt/interfaces.py
strukt/langchain_helpers.py
strukt/llm_clients.py
strukt/logging.py
strukt/optimizations.py
strukt/retry.py
strukt/secrets.py
strukt/tracing.py
strukt/types.py
strukt/utils.py
strukt/classifiers/llm_classifier.py
strukt/examples/__init__.py
strukt/examples/time_handler.py
strukt/extensions/devices/README.md
strukt/extensions/devices/__init__.py
strukt/extensions/devices/handler.py
strukt/extensions/devices/models.py
strukt/extensions/devices/prompts.py
strukt/extensions/devices/toolkit.py
strukt/extensions/devices/transport.py
strukt/extensions/devices/validation.py
strukt/mcp_v2/README.md
strukt/mcp_v2/__init__.py
strukt/mcp_v2/asgi.py
strukt/mcp_v2/auth.py
strukt/mcp_v2/auth_adapter.py
strukt/mcp_v2/fastmcp_server.py
strukt/mcp_v2/handler_adapters.py
strukt/mcp_v2/middleware_bridge.py
strukt/mcp_v2/transports.py
strukt/memory/README_intent_cache.md
strukt/memory/__init__.py
strukt/memory/handler_cache_mixin.py
strukt/memory/intent_cache_engine.py
strukt/memory/intent_cache_types.py
strukt/memory/memory.py
strukt/memory/memory_config.py
strukt/memory/memory_store.py
strukt/memory/memory_types.py
strukt/memory/middleware.py
strukt/memory/examples/intent_cache_example.py
strukt/middleware/__init__.py
strukt/middleware/approval.py
strukt/middleware/background_tasks.py
strukt/middleware/logger.py
strukt/middleware/middleware.py
strukt/middleware/response_cleaner.py
strukt/prompts/__init__.py
strukt/prompts/classifier_prompts.py
strukt/prompts/memory_prompts.py
strukt/prompts/time_prompts.py
strukt/prompts/utils.py
struktx_ai-0.0.4b5.dist-info/METADATA
struktx_ai-0.0.4b5.dist-info/WHEEL
struktx_ai-0.0.4b5.dist-info/entry_points.txt
struktx_ai-0.0.4b5.dist-info/licenses/LICENSE
struktx_ai-0.0.4b5.dist-info/RECORD
