Metadata-Version: 2.4
Name: struktx-ai
Version: 0.0.4b5
Summary: A configurable, typed AI framework with swappable LLM, classifier, handlers, and optional memory
Project-URL: Homepage, https://github.com/snowheapllc/struktx
Project-URL: Documentation, https://struktx.snowheap.ai
Project-URL: Repository, https://github.com/snowheapllc/struktx.git
Project-URL: Bug Tracker, https://github.com/snowheapllc/struktx/issues
Project-URL: Source Code, https://github.com/snowheapllc/struktx
Author-email: Snowheap LLC <info@snowheap.com>
Maintainer-email: Snowheap LLC <info@snowheap.com>
License: MIT
License-File: LICENSE
Keywords: ai,chatbot,framework,langchain,llm,nlp
Classifier: Development Status :: 3 - Alpha
Classifier: Intended Audience :: Developers
Classifier: License :: OSI Approved :: MIT License
Classifier: Operating System :: OS Independent
Classifier: Programming Language :: Python :: 3
Classifier: Programming Language :: Python :: 3.10
Classifier: Programming Language :: Python :: 3.11
Classifier: Programming Language :: Python :: 3.12
Classifier: Topic :: Scientific/Engineering :: Artificial Intelligence
Classifier: Topic :: Software Development :: Libraries :: Python Modules
Requires-Python: >=3.10.0
Requires-Dist: black>=25.1.0
Requires-Dist: boto3>=1.37.38
Requires-Dist: botocore>=1.37.38
Requires-Dist: chromadb>=1.0.20
Requires-Dist: fastapi>=0.116.1
Requires-Dist: fastmcp>=2.12.5
Requires-Dist: httpx>=0.28.1
Requires-Dist: inflect>=7.0.0
Requires-Dist: jellyfish>=1.2.0
Requires-Dist: langchain-community>=0.3.27
Requires-Dist: langchain-core>=0.3.74
Requires-Dist: langchain-openai>=0.3.30
Requires-Dist: lark>=1.2.2
Requires-Dist: mcp[cli]>=1.0.0
Requires-Dist: opentelemetry-api>=1.36.0
Requires-Dist: opentelemetry-exporter-otlp-proto-http>=1.36.0
Requires-Dist: opentelemetry-instrumentation-openai>=0.46.2
Requires-Dist: opentelemetry-sdk>=1.36.0
Requires-Dist: pre-commit>=4.3.0
Requires-Dist: pycountry>=23.12.11
Requires-Dist: pydantic>=2.0.0
Requires-Dist: pytest-asyncio>=1.1.0
Requires-Dist: pytest>=8.4.1
Requires-Dist: python-dotenv>=1.0.0
Requires-Dist: pytz>=2024.1
Requires-Dist: rapidfuzz>=3.14.1
Requires-Dist: requests>=2.31.0
Requires-Dist: rich>=14.1.0
Requires-Dist: ruff>=0.12.10
Requires-Dist: tavily-python>=0.7.12
Requires-Dist: upstash-vector>=0.8.0
Requires-Dist: weave>=0.52.6
Provides-Extra: all
Requires-Dist: chromadb>=0.5.0; extra == 'all'
Requires-Dist: langchain-community>=0.2.0; extra == 'all'
Requires-Dist: langchain-core>=0.1.0; extra == 'all'
Requires-Dist: langchain-openai>=0.1.0; extra == 'all'
Requires-Dist: upstash-vector>=0.1.0; extra == 'all'
Provides-Extra: dev
Requires-Dist: black>=23.0.0; extra == 'dev'
Requires-Dist: pre-commit>=3.0.0; extra == 'dev'
Requires-Dist: pytest-asyncio>=0.21.0; extra == 'dev'
Requires-Dist: pytest>=7.0.0; extra == 'dev'
Requires-Dist: ruff>=0.3.0; extra == 'dev'
Provides-Extra: docs
Requires-Dist: myst-parser>=2.0.0; extra == 'docs'
Requires-Dist: sphinx-rtd-theme>=1.3.0; extra == 'docs'
Requires-Dist: sphinx>=7.0.0; extra == 'docs'
Provides-Extra: llm
Requires-Dist: langchain-community>=0.2.0; extra == 'llm'
Requires-Dist: langchain-core>=0.1.0; extra == 'llm'
Requires-Dist: langchain-openai>=0.1.0; extra == 'llm'
Provides-Extra: vector
Requires-Dist: chromadb>=0.5.0; extra == 'vector'
Requires-Dist: upstash-vector>=0.1.0; extra == 'vector'
Provides-Extra: weave
Requires-Dist: weave>=0.52.6; extra == 'weave'
